context/__init__.py
context/count_tokens.py
context/merge_llms_full_txt.py
context/merge_llms_txt.py
context/utils.py
mseep_videodb_helper-0.1.2.dist-info/METADATA
mseep_videodb_helper-0.1.2.dist-info/WHEEL
mseep_videodb_helper-0.1.2.dist-info/top_level.txt
mseep_videodb_helper-0.1.2.dist-info/RECORD
